telem_util.py
telem_util-0.0.1.dist-info/METADATA
telem_util-0.0.1.dist-info/WHEEL
telem_util-0.0.1.dist-info/top_level.txt
telem_util-0.0.1.dist-info/RECORD
