Metadata-Version: 2.1
Name: telem_util
Version: 0.0.1
Summary: My python package
Author: Rohan Dey Sarkar
Classifier: Programming Language :: Python :: 3
Classifier: License :: OSI Approved :: MIT License
Classifier: Operating System :: OS Independent
Requires-Python: >=3.6
